smart_connection/__init__.py
smart_connection/abstract.py
smart_connection/connection.py
smart_connection/py.typed
smart_connection-0.1.0.dist-info/METADATA
smart_connection-0.1.0.dist-info/WHEEL
smart_connection-0.1.0.dist-info/RECORD
